critics/__init__.py
critics/commands.py
critics/compat.py
critics/core.py
critics/i18n.py
critics/parsers.py
critics/transport.py
critics-0.2.1.dist-info/DESCRIPTION.rst
critics-0.2.1.dist-info/entry_points.txt
critics-0.2.1.dist-info/METADATA
critics-0.2.1.dist-info/metadata.json
critics-0.2.1.dist-info/RECORD
critics-0.2.1.dist-info/top_level.txt
critics-0.2.1.dist-info/WHEEL
