Metadata-Version: 2.0
Name: critics
Version: 0.2.1
Summary: Mobile reviews aggregator
Home-page: https://github.com/coagulant/critics
Author: Ilya Baryshev
Author-email: baryshev@gmail.com
License: BSD
Keywords: critics
Platform: UNKNOWN
Classifier: Development Status :: 4 - Beta
Classifier: Intended Audience :: Developers
Classifier: License :: OSI Approved :: BSD License
Classifier: Natural Language :: English
Classifier: Programming Language :: Python :: 2
Classifier: Programming Language :: Python :: 2.6
Classifier: Programming Language :: Python :: 2.7
Classifier: Programming Language :: Python :: 3
Classifier: Programming Language :: Python :: 3.3
Classifier: Programming Language :: Python :: 3.4
Requires-Dist: requests (>=2.6)
Requires-Dist: tornado (>=4.1)
Requires-Dist: lxml (>=3.4.2)
Requires-Dist: cssselect (>=0.9.1)
Requires-Dist: feedparser (>=5.1.3)
Requires-Dist: click (>=3.3)
Requires-Dist: Babel (>=1.3)
